project/__init__.py
project/main.py
wifiman-0.1.1.0.dist-info/METADATA
wifiman-0.1.1.0.dist-info/WHEEL
wifiman-0.1.1.0.dist-info/entry_points.txt
wifiman-0.1.1.0.dist-info/licenses/LICENSE
wifiman-0.1.1.0.dist-info/RECORD
