Metadata-Version: 2.1
Name: wifiman
Version: 0.1.1.0
Summary: Python based simple WiFi manager for Windows 10/11
Author-Email: Krishnakanth Allika <richly-human-grew@duck.com>
License: GNU GPL v3
Classifier: Development Status :: 3 - Alpha
Classifier: Intended Audience :: End Users/Desktop
Classifier: License :: OSI Approved :: GNU General Public License v3 (GPLv3)
Classifier: Operating System :: Microsoft :: Windows :: Windows 10
Classifier: Operating System :: Microsoft :: Windows :: Windows 11
Classifier: Programming Language :: Python :: 3
Classifier: Programming Language :: Python :: 3.10
Classifier: Programming Language :: Python :: 3.11
Classifier: Programming Language :: Python :: 3.12
Classifier: Topic :: System :: Networking
Classifier: Topic :: Utilities
Project-URL: Homepage, https://go.allika.eu.org/wifiman
Project-URL: Download_Latest_Binary, https://go.allika.eu.org/wifimanlatestbinary
Project-URL: All_Releases, https://go.allika.eu.org/wifimanreleases
Project-URL: Repository, https://go.allika.eu.org/wifimanrepo
Project-URL: Documentation, https://go.allika.eu.org/wifimandocs
Project-URL: Changelog, https://go.allika.eu.org/wifimanchangelog
Requires-Python: >=3.10
Requires-Dist: pyinstaller>=6.13.0
Requires-Dist: pywin32>=310
